scanlt/__init__.py
scanlt/api.py
scanlt/backends.py
scanlt/hw.py
scanlt/model_zoo.py
scanlt/onnx_yolo_seg.py
scanlt3d-0.1.4.dist-info/licenses/LICENSE
scanlt3d-0.1.4.dist-info/METADATA
scanlt3d-0.1.4.dist-info/WHEEL
scanlt3d-0.1.4.dist-info/top_level.txt
scanlt3d-0.1.4.dist-info/RECORD
