Metadata-Version: 2.4
Name: scanlt3d
Version: 0.1.4
Summary: Realtime 3D (depth) + detection pipeline for laptop cameras (OpenCV optional)
Author: scanlt3d contributors
License: MIT License
Project-URL: Homepage, https://github.com/your-org/scanLt
Project-URL: Repository, https://github.com/your-org/scanLt
Project-URL: Issues, https://github.com/your-org/scanLt/issues
Keywords: realtime,camera,depth,detection
Classifier: License :: OSI Approved :: MIT License
Classifier: Programming Language :: Python :: 3
Classifier: Programming Language :: Python :: 3.10
Classifier: Operating System :: OS Independent
Requires-Python: >=3.10
License-File: LICENSE
Requires-Dist: numpy>=1.23
Requires-Dist: pillow>=9.0
Requires-Dist: opencv-python>=4.0
Provides-Extra: onnx
Requires-Dist: onnxruntime>=1.16; extra == "onnx"
Provides-Extra: torch
Requires-Dist: torch>=2.0; extra == "torch"
Provides-Extra: mediapipe
Requires-Dist: mediapipe>=0.10; extra == "mediapipe"
Provides-Extra: opencv
Dynamic: license-file
